django_ip_access/__init__.py
django_ip_access/admin.py
django_ip_access/backends.py
django_ip_access/forms.py
django_ip_access/middleware.py
django_ip_access/models.py
django_ip_access/settings.py
django_ip_access/migrations/0001_initial.py
django_ip_access/migrations/0002_auto_20200204_1233.py
django_ip_access/migrations/0003_auto_20200320_1148.py
django_ip_access/migrations/__init__.py
django_ip_access-3.0.0.dist-info/LICENSE
django_ip_access-3.0.0.dist-info/METADATA
django_ip_access-3.0.0.dist-info/WHEEL
django_ip_access-3.0.0.dist-info/top_level.txt
django_ip_access-3.0.0.dist-info/RECORD
