Metadata-Version: 2.1
Name: django-ip-access
Version: 3.0.0
Summary: Access a Django app with authorized IP address
Home-page: https://github.com/briefmnews/django-ip-access
Author: Brief.me
Author-email: tech@brief.me
License: GNU General Public License v3.0
Classifier: Environment :: Web Environment
Classifier: Framework :: Django
Classifier: Framework :: Django :: 4.2
Classifier: Operating System :: OS Independent
Classifier: Programming Language :: Python
Classifier: Topic :: Software Development :: Libraries :: Python Modules
Classifier: Programming Language :: Python
Classifier: Programming Language :: Python :: 3
Requires-Python: >=3.9
License-File: LICENSE
Requires-Dist: Django>=4.2
Requires-Dist: django-ipware>=2.1
